[
  {
    "url": "https://axellynch.substack.com/p/nu-holdings-nu",
    "title": "NU HOLDINGS Analysis ($NU)",
    "author": "Axel Lynch",
    "platform": "substack",
    "date": "2026-01-01",
    "brief": "Nubank PEG 0.49 strong buy analysis"
  },
  {
    "url": "https://ianbezek.substack.com/p/why-i-a-former-nubank-skeptic-am",
    "title": "Why I, A Former Nubank Skeptic, Am Now Looking For Shares To Triple",
    "author": "Ian Bezek",
    "platform": "substack",
    "date": "2025-12-15",
    "brief": "Former skeptic now bullish on Nubank growth"
  },
  {
    "url": "https://www.potentialmultibaggers.com/p/the-nu-analysis-the-perfect-weekend",
    "title": "The NU Analysis (The Perfect Weekend Read)",
    "author": "Kris",
    "platform": "independent",
    "date": "2025-11-20",
    "brief": "Detailed Nu Holdings earnings analysis"
  },
  {
    "url": "https://lex.substack.com/p/fintech-nubanks-stellar-q2-makes",
    "title": "Fintech: Nubank's stellar Q2 makes the case for a $250B valuation",
    "author": "Lex",
    "platform": "substack",
    "date": "2025-08-20",
    "brief": "Q2 2025 results valuation case $250B"
  },
  {
    "url": "https://denisdoroshenko.substack.com/p/nu-holdings-nu-executive-summary",
    "title": "Nu Holdings (NU) Executive Summary: Why Fundamentals Are ...",
    "author": "Denis Doroshenko",
    "platform": "substack",
    "date": "2026-03-25",
    "brief": "Fundamentals strong despite stock plunge"
  },
  {
    "url": "https://stocksmarts.substack.com/p/nu-holdings-ltd-nu-deep-dive",
    "title": "Nu Holdings Ltd $NU Deep Dive",
    "author": "Mukund Mohan",
    "platform": "substack",
    "date": "2025-10-10",
    "brief": "Deep dive into Nu Holdings financials"
  },
  {
    "url": "https://patientcapitalfund.substack.com/p/nu-holdings-nu",
    "title": "Nu Holdings (NU)",
    "author": "Patient Capital Fund",
    "platform": "substack",
    "date": "2025-09-05",
    "brief": "Structural cost advantages analysis"
  },
  {
    "url": "https://growthstockdeepdives.substack.com/p/part-1-deep-dive-writeup-of-nubank",
    "title": "Part 1: Deep dive writeup of Nubank ($NU)",
    "author": "Growth Stock Deep Dives",
    "platform": "substack",
    "date": "2025-07-15",
    "brief": "Part 1 Nubank deep dive writeup"
  },
  {
    "url": "https://valuepunks.substack.com/p/deep-dive-nu-holdings-nu-us",
    "title": "Deep Dive: NU Holdings (NU US)",
    "author": "Value Punks",
    "platform": "substack",
    "date": "2025-06-30",
    "brief": "Product tech consumer platform deep dive"
  },
  {
    "url": "https://wonderstcks.substack.com/p/nubank",
    "title": "Nubank",
    "author": "Wonder Stocks",
    "platform": "substack",
    "date": "2025-05-20",
    "brief": "Hyper-growth elite efficiency deep dive"
  }
]